pyholo-0.1.8.dist-info/METADATA
pyholo-0.1.8.dist-info/WHEEL
pyholo-0.1.8.dist-info/licenses/LICENSE
pyholo/__init__.py
pyholo/__init__.pyi
pyholo/py.typed
pyholo/pyholo.pyd
pyholo-0.1.8.dist-info/RECORD
