Metadata-Version: 2.4
Name: pyholo
Version: 0.1.8
Classifier: Development Status :: 4 - Beta
Classifier: Intended Audience :: Science/Research
Classifier: Intended Audience :: Developers
Classifier: Programming Language :: Rust
Classifier: Programming Language :: Python :: 3
Classifier: Programming Language :: Python :: 3.10
Classifier: Programming Language :: Python :: 3.11
Classifier: Programming Language :: Python :: 3.12
Classifier: Topic :: Scientific/Engineering
Classifier: Topic :: Scientific/Engineering :: Mathematics
Classifier: Topic :: Software Development :: Libraries :: Python Modules
License-File: LICENSE
Summary: Multipurpose interpolation library focussing on RBF, written in rust.
Keywords: interpolation,rbf,radial basis function,scientific computing,numerical methods,data science,machine learning
Author-email: Aleksander Lovric <alexlovric@gmail.com>
License: MIT
Requires-Python: >=3.10
